autodocstring/__init__.py
autodocstring/autodocstring.py
tests/__init__.py
autodocstring-0.1.2.dist-info/METADATA
autodocstring-0.1.2.dist-info/WHEEL
autodocstring-0.1.2.dist-info/entry_points.txt
autodocstring-0.1.2.dist-info/top_level.txt
autodocstring-0.1.2.dist-info/RECORD
