Metadata-Version: 2.2
Name: autodocstring
Version: 0.1.2
Summary: A Python package for generating docstrings automatically.
Home-page: https://github.com/eduardonery1/autodocstring
Author: Your Name
Author-email: your_email@example.com
License: MIT
Classifier: Programming Language :: Python :: 3
Classifier: License :: OSI Approved :: MIT License
Classifier: Operating System :: OS Independent
Requires-Python: >=3.6
Requires-Dist: python-dotenv
Requires-Dist: google-generativeai
Dynamic: author
Dynamic: author-email
Dynamic: classifier
Dynamic: description
Dynamic: description-content-type
Dynamic: home-page
Dynamic: license
Dynamic: requires-dist
Dynamic: requires-python
Dynamic: summary
